outlier_model
